emyo/__init__.py
emyo/common.py
emyo/emyo.py
emyo-0.0.2.dist-info/LICENSE
emyo-0.0.2.dist-info/METADATA
emyo-0.0.2.dist-info/WHEEL
emyo-0.0.2.dist-info/top_level.txt
emyo-0.0.2.dist-info/RECORD
