Metadata-Version: 2.1
Name: emyo
Version: 0.0.2
Summary: An interactive map for children
Home-page: https://github.com/geofixit/emyo
Author: Edmar Tabamo
Author-email: geoed316@gmail.com
License: MIT license
Keywords: emyo
Classifier: Intended Audience :: Developers
Classifier: License :: OSI Approved :: MIT License
Classifier: Natural Language :: English
Classifier: Programming Language :: Python :: 3
Classifier: Programming Language :: Python :: 3.8
Classifier: Programming Language :: Python :: 3.9
Classifier: Programming Language :: Python :: 3.10
Classifier: Programming Language :: Python :: 3.11
Requires-Python: >=3.8
License-File: LICENSE
